aistac/__init__.py
aistac/components/__init__.py
aistac/components/abstract_component.py
aistac/components/aistac_commons.py
aistac/handlers/__init__.py
aistac/handlers/abstract_event_book.py
aistac/handlers/abstract_handlers.py
aistac/handlers/parsers.py
aistac/handlers/python_handlers.py
aistac/intent/__init__.py
aistac/intent/abstract_intent.py
aistac/intent/python_cleaners_intent.py
aistac/properties/__init__.py
aistac/properties/abstract_properties.py
aistac/properties/decorator_patterns.py
aistac/properties/property_manager.py
tests/components/__init__.py
tests/components/abstract_component_test.py
tests/components/commons_test.py
tests/handlers/__init__.py
tests/handlers/connector_contract_test.py
tests/handlers/handler_factory_test.py
tests/handlers/python_handler_test.py
tests/intent/__init__.py
tests/intent/abstract_intent_test.py
tests/properties/__init__.py
tests/properties/abstract_properties_manager_test.py
tests/properties/property_manager_test.py
tests/test_data/__init__.py
tests/test_data/contracts/__init__.py
aistac_foundation-2.17.5.dist-info/LICENSE.txt
aistac_foundation-2.17.5.dist-info/METADATA
aistac_foundation-2.17.5.dist-info/WHEEL
aistac_foundation-2.17.5.dist-info/top_level.txt
aistac_foundation-2.17.5.dist-info/RECORD
