Metadata-Version: 2.1
Name: aistac-foundation
Version: 2.17.5
Summary: Augmented Intent Single Task Adaptive Components
Home-page: http://github.com/gigas64/aistac-foundation
Author: Gigas64
Author-email: gigas64@aistac.com
License: BSD
Keywords: Foundation SDK Machine learning AI component intent data science
Classifier: Development Status :: 5 - Production/Stable
Classifier: License :: OSI Approved :: BSD License
Classifier: Intended Audience :: Developers
Classifier: Intended Audience :: Science/Research
Classifier: Programming Language :: Python :: 3.7
Classifier: Programming Language :: Python :: 3.8
Classifier: Programming Language :: Python :: 3.9
Classifier: Topic :: Adaptive Technologies
Classifier: Topic :: Scientific/Engineering :: Artificial Intelligence
Classifier: Topic :: Scientific/Engineering :: Information Analysis
Classifier: Topic :: Software Development :: Libraries :: Python Modules
Requires-Python: >=3.7
License-File: LICENSE.txt
